idsprites/__init__.py
idsprites/continual_benchmark.py
idsprites/infinite_dsprites.py
idsprites/visualization.py
idsprites-1.0.1.dist-info/METADATA
idsprites-1.0.1.dist-info/WHEEL
idsprites-1.0.1.dist-info/licenses/LICENSE
idsprites-1.0.1.dist-info/RECORD
