Metadata-Version: 2.3
Name: idsprites
Version: 1.0.1
Summary: Easily generate simple continual learning benchmarks.
Author-email: Sebastian Dziadzio <dziadzio@hey.com>
License-File: LICENSE
Requires-Python: >=3.10
Requires-Dist: imageio>=2.13.0
Requires-Dist: matplotlib>=3.8.2
Requires-Dist: numba>=0.58.1
Requires-Dist: numpy>=1.26.2
Requires-Dist: omegaconf>=2.3.0
Requires-Dist: opencv-python>=4.8.1
Requires-Dist: scikit-learn>=1.3.2
Requires-Dist: scipy>=1.11.4
Requires-Dist: torch>=2.1.2
Requires-Dist: tqdm>=4.66.1
